{
 "custom_fields": [
  {
   "_assign": null,
   "_comments": null,
   "_liked_by": null,
   "_user_tags": null,
   "allow_in_quick_entry": 0,
   "allow_on_submit": 0,
   "bold": 0,
   "collapsible": 0,
   "collapsible_depends_on": null,
   "columns": 0,
   "creation": "2021-02-13 01:27:22.183233",
   "default": null,
   "depends_on": null,
   "description": null,
   "docstatus": 0,
   "dt": "Delivery Note",
   "fetch_from": null,
   "fetch_if_empty": 0,
   "fieldname": "purchase_order",
   "fieldtype": "Link",
   "hidden": 0,
   "hide_border": 0,
   "hide_days": 0,
   "hide_seconds": 0,
   "idx": 146,
   "ignore_user_permissions": 0,
   "ignore_xss_filter": 0,
   "in_global_search": 0,
   "in_list_view": 0,
   "in_preview": 0,
   "in_standard_filter": 0,
   "insert_after": "department",
   "label": "Purchase Order",
   "length": 0,
   "mandatory_depends_on": null,
   "modified": "2021-02-13 01:27:22.183233",
   "modified_by": "mbadea@injaztech.net",
   "name": "Delivery Note-purchase_order",
   "no_copy": 0,
   "non_negative": 0,
   "options": "Purchase Order",
   "owner": "Administrator",
   "parent": null,
   "parentfield": null,
   "parenttype": null,
   "permlevel": 0,
   "precision": "",
   "print_hide": 0,
   "print_hide_if_no_value": 0,
   "print_width": null,
   "read_only": 0,
   "read_only_depends_on": null,
   "report_hide": 0,
   "reqd": 0,
   "search_index": 0,
   "translatable": 0,
   "unique": 0,
   "width": null
  },
  {
   "_assign": null,
   "_comments": null,
   "_liked_by": null,
   "_user_tags": null,
   "allow_in_quick_entry": 0,
   "allow_on_submit": 0,
   "bold": 0,
   "collapsible": 0,
   "collapsible_depends_on": null,
   "columns": 0,
   "creation": "2021-02-13 15:25:42.654382",
   "default": null,
   "depends_on": null,
   "description": null,
   "docstatus": 0,
   "dt": "Delivery Note",
   "fetch_from": null,
   "fetch_if_empty": 0,
   "fieldname": "department",
   "fieldtype": "Link",
   "hidden": 0,
   "hide_border": 0,
   "hide_days": 0,
   "hide_seconds": 0,
   "idx": 145,
   "ignore_user_permissions": 0,
   "ignore_xss_filter": 0,
   "in_global_search": 0,
   "in_list_view": 0,
   "in_preview": 0,
   "in_standard_filter": 0,
   "insert_after": "sales_team",
   "label": "Department",
   "length": 0,
   "mandatory_depends_on": null,
   "modified": "2021-02-13 15:25:42.654382",
   "modified_by": "mbadea@injaztech.net",
   "name": "Delivery Note-department",
   "no_copy": 0,
   "non_negative": 0,
   "options": "Department",
   "owner": "Administrator",
   "parent": null,
   "parentfield": null,
   "parenttype": null,
   "permlevel": 0,
   "precision": "",
   "print_hide": 0,
   "print_hide_if_no_value": 0,
   "print_width": null,
   "read_only": 0,
   "read_only_depends_on": null,
   "report_hide": 0,
   "reqd": 0,
   "search_index": 0,
   "translatable": 0,
   "unique": 0,
   "width": null
  },
  {
   "_assign": null,
   "_comments": null,
   "_liked_by": null,
   "_user_tags": null,
   "allow_in_quick_entry": 0,
   "allow_on_submit": 1,
   "bold": 0,
   "collapsible": 0,
   "collapsible_depends_on": null,
   "columns": 0,
   "creation": "2021-11-20 16:31:44.405337",
   "default": null,
   "depends_on": null,
   "description": null,
   "docstatus": 0,
   "dt": "Delivery Note",
   "fetch_from": null,
   "fetch_if_empty": 0,
   "fieldname": "workflow_state",
   "fieldtype": "Link",
   "hidden": 1,
   "hide_border": 0,
   "hide_days": 0,
   "hide_seconds": 0,
   "idx": 1,
   "ignore_user_permissions": 0,
   "ignore_xss_filter": 0,
   "in_global_search": 0,
   "in_list_view": 0,
   "in_preview": 0,
   "in_standard_filter": 0,
   "insert_after": null,
   "label": "Workflow State",
   "length": 0,
   "mandatory_depends_on": null,
   "modified": "2021-11-20 16:31:44.405337",
   "modified_by": "Administrator",
   "name": "Delivery Note-workflow_state",
   "no_copy": 1,
   "non_negative": 0,
   "options": "Workflow State",
   "owner": "Administrator",
   "parent": null,
   "parentfield": null,
   "parenttype": null,
   "permlevel": 0,
   "precision": "",
   "print_hide": 0,
   "print_hide_if_no_value": 0,
   "print_width": null,
   "read_only": 0,
   "read_only_depends_on": null,
   "report_hide": 0,
   "reqd": 0,
   "search_index": 0,
   "translatable": 0,
   "unique": 0,
   "width": null
  },
  {
   "_assign": null,
   "_comments": null,
   "_liked_by": null,
   "_user_tags": null,
   "allow_in_quick_entry": 0,
   "allow_on_submit": 0,
   "bold": 0,
   "collapsible": 0,
   "collapsible_depends_on": null,
   "columns": 0,
   "creation": "2021-11-20 16:37:02.431152",
   "default": null,
   "depends_on": "",
   "description": null,
   "docstatus": 0,
   "dt": "Delivery Note",
   "fetch_from": null,
   "fetch_if_empty": 0,
   "fieldname": "attach",
   "fieldtype": "Attach",
   "hidden": 0,
   "hide_border": 0,
   "hide_days": 0,
   "hide_seconds": 0,
   "idx": 109,
   "ignore_user_permissions": 0,
   "ignore_xss_filter": 0,
   "in_global_search": 0,
   "in_list_view": 0,
   "in_preview": 0,
   "in_standard_filter": 0,
   "insert_after": "more_info",
   "label": "Attach",
   "length": 0,
   "mandatory_depends_on": "",
   "modified": "2021-11-20 16:37:02.431152",
   "modified_by": "Administrator",
   "name": "Delivery Note-attach",
   "no_copy": 0,
   "non_negative": 0,
   "options": null,
   "owner": "Administrator",
   "parent": null,
   "parentfield": null,
   "parenttype": null,
   "permlevel": 0,
   "precision": "",
   "print_hide": 0,
   "print_hide_if_no_value": 0,
   "print_width": null,
   "read_only": 0,
   "read_only_depends_on": null,
   "report_hide": 0,
   "reqd": 0,
   "search_index": 0,
   "translatable": 0,
   "unique": 0,
   "width": null
  }
 ],
 "custom_perms": [
  {
   "_assign": null,
   "_comments": null,
   "_liked_by": null,
   "_user_tags": null,
   "amend": 0,
   "cancel": 0,
   "create": 0,
   "creation": "2022-05-26 00:43:34.367547",
   "delete": 0,
   "docstatus": 0,
   "email": 0,
   "export": 1,
   "idx": 0,
   "if_owner": 0,
   "import": 0,
   "modified": "2022-05-26 00:43:34.367547",
   "modified_by": "Administrator",
   "name": "d9ca251080",
   "owner": "Administrator",
   "parent": "Delivery Note",
   "parentfield": null,
   "parenttype": null,
   "permlevel": 1,
   "print": 0,
   "read": 1,
   "report": 0,
   "role": "New Account",
   "select": 0,
   "set_user_permissions": 0,
   "share": 0,
   "submit": 0,
   "write": 1
  },
  {
   "_assign": null,
   "_comments": null,
   "_liked_by": null,
   "_user_tags": null,
   "amend": 0,
   "cancel": 0,
   "create": 0,
   "creation": "2022-05-26 00:43:51.230492",
   "delete": 0,
   "docstatus": 0,
   "email": 0,
   "export": 0,
   "idx": 0,
   "if_owner": 0,
   "import": 0,
   "modified": "2022-05-26 00:43:51.230492",
   "modified_by": "Administrator",
   "name": "5e871c1bb9",
   "owner": "Administrator",
   "parent": "Delivery Note",
   "parentfield": null,
   "parenttype": null,
   "permlevel": 0,
   "print": 0,
   "read": 1,
   "report": 1,
   "role": "Accounts User",
   "select": 0,
   "set_user_permissions": 0,
   "share": 0,
   "submit": 0,
   "write": 0
  },
  {
   "_assign": null,
   "_comments": null,
   "_liked_by": null,
   "_user_tags": null,
   "amend": 1,
   "cancel": 1,
   "create": 1,
   "creation": "2022-05-26 00:43:51.252545",
   "delete": 1,
   "docstatus": 0,
   "email": 1,
   "export": 0,
   "idx": 0,
   "if_owner": 0,
   "import": 0,
   "modified": "2022-05-26 00:43:51.252545",
   "modified_by": "Administrator",
   "name": "8a34cf0138",
   "owner": "Administrator",
   "parent": "Delivery Note",
   "parentfield": null,
   "parenttype": null,
   "permlevel": 0,
   "print": 1,
   "read": 1,
   "report": 1,
   "role": "Sales User",
   "select": 0,
   "set_user_permissions": 0,
   "share": 1,
   "submit": 1,
   "write": 1
  },
  {
   "_assign": null,
   "_comments": null,
   "_liked_by": null,
   "_user_tags": null,
   "amend": 0,
   "cancel": 0,
   "create": 0,
   "creation": "2022-05-26 00:43:51.273389",
   "delete": 0,
   "docstatus": 0,
   "email": 0,
   "export": 0,
   "idx": 0,
   "if_owner": 0,
   "import": 0,
   "modified": "2022-05-26 00:43:51.273389",
   "modified_by": "Administrator",
   "name": "832449bd99",
   "owner": "Administrator",
   "parent": "Delivery Note",
   "parentfield": null,
   "parenttype": null,
   "permlevel": 1,
   "print": 0,
   "read": 1,
   "report": 0,
   "role": "Stock Manager",
   "select": 0,
   "set_user_permissions": 0,
   "share": 0,
   "submit": 0,
   "write": 1
  },
  {
   "_assign": null,
   "_comments": null,
   "_liked_by": null,
   "_user_tags": null,
   "amend": 0,
   "cancel": 0,
   "create": 0,
   "creation": "2022-05-26 00:43:51.294112",
   "delete": 0,
   "docstatus": 0,
   "email": 0,
   "export": 0,
   "idx": 0,
   "if_owner": 0,
   "import": 0,
   "modified": "2022-05-26 00:43:51.294112",
   "modified_by": "Administrator",
   "name": "8e843b2162",
   "owner": "Administrator",
   "parent": "Delivery Note",
   "parentfield": null,
   "parenttype": null,
   "permlevel": 0,
   "print": 0,
   "read": 1,
   "report": 1,
   "role": "Stock User",
   "select": 0,
   "set_user_permissions": 0,
   "share": 0,
   "submit": 0,
   "write": 0
  },
  {
   "_assign": null,
   "_comments": null,
   "_liked_by": null,
   "_user_tags": null,
   "amend": 1,
   "cancel": 1,
   "create": 1,
   "creation": "2022-05-26 00:43:51.316901",
   "delete": 1,
   "docstatus": 0,
   "email": 1,
   "export": 0,
   "idx": 0,
   "if_owner": 0,
   "import": 0,
   "modified": "2022-05-26 00:43:51.316901",
   "modified_by": "Administrator",
   "name": "2210ca0d9c",
   "owner": "Administrator",
   "parent": "Delivery Note",
   "parentfield": null,
   "parenttype": null,
   "permlevel": 0,
   "print": 1,
   "read": 1,
   "report": 1,
   "role": "Stock Manager",
   "select": 0,
   "set_user_permissions": 0,
   "share": 1,
   "submit": 1,
   "write": 1
  },
  {
   "_assign": null,
   "_comments": null,
   "_liked_by": null,
   "_user_tags": null,
   "amend": 1,
   "cancel": 0,
   "create": 1,
   "creation": "2022-05-26 00:43:51.339209",
   "delete": 0,
   "docstatus": 0,
   "email": 0,
   "export": 1,
   "idx": 0,
   "if_owner": 0,
   "import": 0,
   "modified": "2022-05-26 00:43:51.339209",
   "modified_by": "Administrator",
   "name": "a70938a17e",
   "owner": "Administrator",
   "parent": "Delivery Note",
   "parentfield": null,
   "parenttype": null,
   "permlevel": 0,
   "print": 1,
   "read": 1,
   "report": 1,
   "role": "Project Manager",
   "select": 1,
   "set_user_permissions": 0,
   "share": 0,
   "submit": 1,
   "write": 1
  },
  {
   "_assign": null,
   "_comments": null,
   "_liked_by": null,
   "_user_tags": null,
   "amend": 1,
   "cancel": 0,
   "create": 1,
   "creation": "2022-05-26 00:43:51.889606",
   "delete": 0,
   "docstatus": 0,
   "email": 0,
   "export": 0,
   "idx": 0,
   "if_owner": 0,
   "import": 0,
   "modified": "2022-05-26 00:43:51.889606",
   "modified_by": "Administrator",
   "name": "00528a6a89",
   "owner": "Administrator",
   "parent": "Delivery Note",
   "parentfield": null,
   "parenttype": null,
   "permlevel": 0,
   "print": 1,
   "read": 1,
   "report": 1,
   "role": "Delivery Note Creation",
   "select": 1,
   "set_user_permissions": 0,
   "share": 0,
   "submit": 0,
   "write": 1
  },
  {
   "_assign": null,
   "_comments": null,
   "_liked_by": null,
   "_user_tags": null,
   "amend": 1,
   "cancel": 0,
   "create": 1,
   "creation": "2022-05-26 00:43:52.547505",
   "delete": 0,
   "docstatus": 0,
   "email": 0,
   "export": 0,
   "idx": 0,
   "if_owner": 0,
   "import": 0,
   "modified": "2022-05-26 00:43:52.547505",
   "modified_by": "Administrator",
   "name": "0b8cc3ffd3",
   "owner": "Administrator",
   "parent": "Delivery Note",
   "parentfield": null,
   "parenttype": null,
   "permlevel": 0,
   "print": 0,
   "read": 1,
   "report": 1,
   "role": "New Account",
   "select": 0,
   "set_user_permissions": 0,
   "share": 0,
   "submit": 1,
   "write": 1
  },
  {
   "_assign": null,
   "_comments": null,
   "_liked_by": null,
   "_user_tags": null,
   "amend": 1,
   "cancel": 0,
   "create": 1,
   "creation": "2022-05-26 00:43:52.891741",
   "delete": 0,
   "docstatus": 0,
   "email": 0,
   "export": 1,
   "idx": 0,
   "if_owner": 0,
   "import": 0,
   "modified": "2022-05-26 00:43:52.891741",
   "modified_by": "Administrator",
   "name": "2c25861915",
   "owner": "Administrator",
   "parent": "Delivery Note",
   "parentfield": null,
   "parenttype": null,
   "permlevel": 0,
   "print": 1,
   "read": 1,
   "report": 1,
   "role": "Accounts Manager",
   "select": 1,
   "set_user_permissions": 0,
   "share": 0,
   "submit": 1,
   "write": 1
  },
  {
   "_assign": null,
   "_comments": null,
   "_liked_by": null,
   "_user_tags": null,
   "amend": 0,
   "cancel": 0,
   "create": 0,
   "creation": "2022-05-26 00:43:53.298493",
   "delete": 0,
   "docstatus": 0,
   "email": 0,
   "export": 1,
   "idx": 0,
   "if_owner": 0,
   "import": 0,
   "modified": "2022-05-26 00:43:53.298493",
   "modified_by": "Administrator",
   "name": "f9681765be",
   "owner": "Administrator",
   "parent": "Delivery Note",
   "parentfield": null,
   "parenttype": null,
   "permlevel": 1,
   "print": 0,
   "read": 1,
   "report": 0,
   "role": "Accounts Manager",
   "select": 0,
   "set_user_permissions": 0,
   "share": 0,
   "submit": 0,
   "write": 0
  },
  {
   "_assign": null,
   "_comments": null,
   "_liked_by": null,
   "_user_tags": null,
   "amend": 0,
   "cancel": 0,
   "create": 0,
   "creation": "2022-05-26 00:43:53.323054",
   "delete": 0,
   "docstatus": 0,
   "email": 0,
   "export": 1,
   "idx": 0,
   "if_owner": 0,
   "import": 0,
   "modified": "2022-05-26 00:43:53.323054",
   "modified_by": "Administrator",
   "name": "cce7299078",
   "owner": "Administrator",
   "parent": "Delivery Note",
   "parentfield": null,
   "parenttype": null,
   "permlevel": 1,
   "print": 0,
   "read": 1,
   "report": 0,
   "role": "Accounts User",
   "select": 0,
   "set_user_permissions": 0,
   "share": 0,
   "submit": 0,
   "write": 0
  },
  {
   "_assign": null,
   "_comments": null,
   "_liked_by": null,
   "_user_tags": null,
   "amend": 0,
   "cancel": 0,
   "create": 0,
   "creation": "2022-05-26 00:43:53.345728",
   "delete": 0,
   "docstatus": 0,
   "email": 0,
   "export": 1,
   "idx": 0,
   "if_owner": 0,
   "import": 0,
   "modified": "2022-05-26 00:43:53.345728",
   "modified_by": "Administrator",
   "name": "73743cd1d7",
   "owner": "Administrator",
   "parent": "Delivery Note",
   "parentfield": null,
   "parenttype": null,
   "permlevel": 1,
   "print": 0,
   "read": 1,
   "report": 0,
   "role": "Sales User",
   "select": 0,
   "set_user_permissions": 0,
   "share": 0,
   "submit": 0,
   "write": 0
  },
  {
   "_assign": null,
   "_comments": null,
   "_liked_by": null,
   "_user_tags": null,
   "amend": 0,
   "cancel": 0,
   "create": 0,
   "creation": "2022-05-26 00:43:53.370363",
   "delete": 0,
   "docstatus": 0,
   "email": 0,
   "export": 1,
   "idx": 0,
   "if_owner": 0,
   "import": 0,
   "modified": "2022-05-26 00:43:53.370363",
   "modified_by": "Administrator",
   "name": "051dfb2d98",
   "owner": "Administrator",
   "parent": "Delivery Note",
   "parentfield": null,
   "parenttype": null,
   "permlevel": 1,
   "print": 0,
   "read": 1,
   "report": 0,
   "role": "Project Manager",
   "select": 0,
   "set_user_permissions": 0,
   "share": 0,
   "submit": 0,
   "write": 0
  }
 ],
 "doctype": "Delivery Note",
 "property_setters": [
  {
   "_assign": null,
   "_comments": null,
   "_liked_by": null,
   "_user_tags": null,
   "creation": "2022-06-21 13:14:40.140999",
   "default_value": null,
   "doc_type": "Delivery Note",
   "docstatus": 0,
   "doctype_or_field": "DocField",
   "field_name": "in_words",
   "idx": 0,
   "modified": "2022-06-21 13:14:40.140999",
   "modified_by": "m.khaled@erpcloud.systems",
   "name": "Delivery Note-in_words-print_hide",
   "owner": "m.khaled@erpcloud.systems",
   "parent": null,
   "parentfield": null,
   "parenttype": null,
   "property": "print_hide",
   "property_type": "Check",
   "row_name": null,
   "value": "0"
  },
  {
   "_assign": null,
   "_comments": null,
   "_liked_by": null,
   "_user_tags": null,
   "creation": "2022-06-21 13:14:40.112985",
   "default_value": null,
   "doc_type": "Delivery Note",
   "docstatus": 0,
   "doctype_or_field": "DocField",
   "field_name": "in_words",
   "idx": 0,
   "modified": "2022-06-21 13:14:40.112985",
   "modified_by": "m.khaled@erpcloud.systems",
   "name": "Delivery Note-in_words-hidden",
   "owner": "m.khaled@erpcloud.systems",
   "parent": null,
   "parentfield": null,
   "parenttype": null,
   "property": "hidden",
   "property_type": "Check",
   "row_name": null,
   "value": "0"
  },
  {
   "_assign": null,
   "_comments": null,
   "_liked_by": null,
   "_user_tags": null,
   "creation": "2022-06-21 13:14:39.341177",
   "default_value": null,
   "doc_type": "Delivery Note",
   "docstatus": 0,
   "doctype_or_field": "DocField",
   "field_name": "disable_rounded_total",
   "idx": 0,
   "modified": "2022-06-21 13:14:39.341177",
   "modified_by": "m.khaled@erpcloud.systems",
   "name": "Delivery Note-disable_rounded_total-default",
   "owner": "m.khaled@erpcloud.systems",
   "parent": null,
   "parentfield": null,
   "parenttype": null,
   "property": "default",
   "property_type": "Text",
   "row_name": null,
   "value": "0"
  },
  {
   "_assign": null,
   "_comments": null,
   "_liked_by": null,
   "_user_tags": null,
   "creation": "2022-06-21 13:14:39.314340",
   "default_value": null,
   "doc_type": "Delivery Note",
   "docstatus": 0,
   "doctype_or_field": "DocField",
   "field_name": "rounded_total",
   "idx": 0,
   "modified": "2022-06-21 13:14:39.314340",
   "modified_by": "m.khaled@erpcloud.systems",
   "name": "Delivery Note-rounded_total-print_hide",
   "owner": "m.khaled@erpcloud.systems",
   "parent": null,
   "parentfield": null,
   "parenttype": null,
   "property": "print_hide",
   "property_type": "Check",
   "row_name": null,
   "value": "0"
  },
  {
   "_assign": null,
   "_comments": null,
   "_liked_by": null,
   "_user_tags": null,
   "creation": "2022-06-21 13:14:39.286642",
   "default_value": null,
   "doc_type": "Delivery Note",
   "docstatus": 0,
   "doctype_or_field": "DocField",
   "field_name": "rounded_total",
   "idx": 0,
   "modified": "2022-06-21 13:14:39.286642",
   "modified_by": "m.khaled@erpcloud.systems",
   "name": "Delivery Note-rounded_total-hidden",
   "owner": "m.khaled@erpcloud.systems",
   "parent": null,
   "parentfield": null,
   "parenttype": null,
   "property": "hidden",
   "property_type": "Check",
   "row_name": null,
   "value": "0"
  },
  {
   "_assign": null,
   "_comments": null,
   "_liked_by": null,
   "_user_tags": null,
   "creation": "2022-06-21 13:14:39.259250",
   "default_value": null,
   "doc_type": "Delivery Note",
   "docstatus": 0,
   "doctype_or_field": "DocField",
   "field_name": "base_rounded_total",
   "idx": 0,
   "modified": "2022-06-21 13:14:39.259250",
   "modified_by": "m.khaled@erpcloud.systems",
   "name": "Delivery Note-base_rounded_total-print_hide",
   "owner": "m.khaled@erpcloud.systems",
   "parent": null,
   "parentfield": null,
   "parenttype": null,
   "property": "print_hide",
   "property_type": "Check",
   "row_name": null,
   "value": "1"
  },
  {
   "_assign": null,
   "_comments": null,
   "_liked_by": null,
   "_user_tags": null,
   "creation": "2022-06-21 13:14:39.230946",
   "default_value": null,
   "doc_type": "Delivery Note",
   "docstatus": 0,
   "doctype_or_field": "DocField",
   "field_name": "base_rounded_total",
   "idx": 0,
   "modified": "2022-06-21 13:14:39.230946",
   "modified_by": "m.khaled@erpcloud.systems",
   "name": "Delivery Note-base_rounded_total-hidden",
   "owner": "m.khaled@erpcloud.systems",
   "parent": null,
   "parentfield": null,
   "parenttype": null,
   "property": "hidden",
   "property_type": "Check",
   "row_name": null,
   "value": "0"
  },
  {
   "_assign": null,
   "_comments": null,
   "_liked_by": null,
   "_user_tags": null,
   "creation": "2022-06-19 09:31:13.163592",
   "default_value": null,
   "doc_type": "Delivery Note",
   "docstatus": 0,
   "doctype_or_field": "DocField",
   "field_name": "scan_barcode",
   "idx": 0,
   "modified": "2022-06-19 09:31:13.163592",
   "modified_by": "islam@erpcloud.systems",
   "name": "Delivery Note-scan_barcode-hidden",
   "owner": "islam@erpcloud.systems",
   "parent": null,
   "parentfield": null,
   "parenttype": null,
   "property": "hidden",
   "property_type": "Check",
   "row_name": null,
   "value": "0"
  },
  {
   "_assign": null,
   "_comments": null,
   "_liked_by": null,
   "_user_tags": null,
   "creation": "2022-06-04 15:44:51.938389",
   "default_value": null,
   "doc_type": "Delivery Note",
   "docstatus": 0,
   "doctype_or_field": "DocField",
   "field_name": "total_commission",
   "idx": 0,
   "modified": "2022-06-04 15:44:51.938389",
   "modified_by": "islam@erpcloud.systems",
   "name": "Delivery Note-total_commission-permlevel",
   "owner": "islam@erpcloud.systems",
   "parent": null,
   "parentfield": null,
   "parenttype": null,
   "property": "permlevel",
   "property_type": "Int",
   "row_name": null,
   "value": "1"
  },
  {
   "_assign": null,
   "_comments": null,
   "_liked_by": null,
   "_user_tags": null,
   "creation": "2022-06-04 15:44:51.862609",
   "default_value": null,
   "doc_type": "Delivery Note",
   "docstatus": 0,
   "doctype_or_field": "DocField",
   "field_name": "commission_rate",
   "idx": 0,
   "modified": "2022-06-04 15:44:51.862609",
   "modified_by": "islam@erpcloud.systems",
   "name": "Delivery Note-commission_rate-permlevel",
   "owner": "islam@erpcloud.systems",
   "parent": null,
   "parentfield": null,
   "parenttype": null,
   "property": "permlevel",
   "property_type": "Int",
   "row_name": null,
   "value": "1"
  },
  {
   "_assign": null,
   "_comments": null,
   "_liked_by": null,
   "_user_tags": null,
   "creation": "2022-06-04 15:44:51.768162",
   "default_value": null,
   "doc_type": "Delivery Note",
   "docstatus": 0,
   "doctype_or_field": "DocField",
   "field_name": "sales_team_section_break",
   "idx": 0,
   "modified": "2022-06-04 15:44:51.768162",
   "modified_by": "islam@erpcloud.systems",
   "name": "Delivery Note-sales_team_section_break-permlevel",
   "owner": "islam@erpcloud.systems",
   "parent": null,
   "parentfield": null,
   "parenttype": null,
   "property": "permlevel",
   "property_type": "Int",
   "row_name": null,
   "value": "1"
  },
  {
   "_assign": null,
   "_comments": null,
   "_liked_by": null,
   "_user_tags": null,
   "creation": "2022-06-04 15:44:15.048045",
   "default_value": null,
   "doc_type": "Delivery Note",
   "docstatus": 0,
   "doctype_or_field": "DocField",
   "field_name": "discount_amount",
   "idx": 0,
   "modified": "2022-06-04 15:44:15.048045",
   "modified_by": "islam@erpcloud.systems",
   "name": "Delivery Note-discount_amount-permlevel",
   "owner": "islam@erpcloud.systems",
   "parent": null,
   "parentfield": null,
   "parenttype": null,
   "property": "permlevel",
   "property_type": "Int",
   "row_name": null,
   "value": "1"
  },
  {
   "_assign": null,
   "_comments": null,
   "_liked_by": null,
   "_user_tags": null,
   "creation": "2022-06-04 15:44:14.971391",
   "default_value": null,
   "doc_type": "Delivery Note",
   "docstatus": 0,
   "doctype_or_field": "DocField",
   "field_name": "additional_discount_percentage",
   "idx": 0,
   "modified": "2022-06-04 15:44:14.971391",
   "modified_by": "islam@erpcloud.systems",
   "name": "Delivery Note-additional_discount_percentage-permlevel",
   "owner": "islam@erpcloud.systems",
   "parent": null,
   "parentfield": null,
   "parenttype": null,
   "property": "permlevel",
   "property_type": "Int",
   "row_name": null,
   "value": "1"
  },
  {
   "_assign": null,
   "_comments": null,
   "_liked_by": null,
   "_user_tags": null,
   "creation": "2022-06-04 15:44:14.885301",
   "default_value": null,
   "doc_type": "Delivery Note",
   "docstatus": 0,
   "doctype_or_field": "DocField",
   "field_name": "base_discount_amount",
   "idx": 0,
   "modified": "2022-06-04 15:44:14.885301",
   "modified_by": "islam@erpcloud.systems",
   "name": "Delivery Note-base_discount_amount-permlevel",
   "owner": "islam@erpcloud.systems",
   "parent": null,
   "parentfield": null,
   "parenttype": null,
   "property": "permlevel",
   "property_type": "Int",
   "row_name": null,
   "value": "1"
  },
  {
   "_assign": null,
   "_comments": null,
   "_liked_by": null,
   "_user_tags": null,
   "creation": "2022-06-04 15:44:14.791341",
   "default_value": null,
   "doc_type": "Delivery Note",
   "docstatus": 0,
   "doctype_or_field": "DocField",
   "field_name": "apply_discount_on",
   "idx": 0,
   "modified": "2022-06-04 15:44:14.791341",
   "modified_by": "islam@erpcloud.systems",
   "name": "Delivery Note-apply_discount_on-permlevel",
   "owner": "islam@erpcloud.systems",
   "parent": null,
   "parentfield": null,
   "parenttype": null,
   "property": "permlevel",
   "property_type": "Int",
   "row_name": null,
   "value": "1"
  },
  {
   "_assign": null,
   "_comments": null,
   "_liked_by": null,
   "_user_tags": null,
   "creation": "2022-06-04 15:43:19.560189",
   "default_value": null,
   "doc_type": "Delivery Note",
   "docstatus": 0,
   "doctype_or_field": "DocField",
   "field_name": "other_charges_calculation",
   "idx": 0,
   "modified": "2022-06-04 15:43:19.560189",
   "modified_by": "islam@erpcloud.systems",
   "name": "Delivery Note-other_charges_calculation-permlevel",
   "owner": "islam@erpcloud.systems",
   "parent": null,
   "parentfield": null,
   "parenttype": null,
   "property": "permlevel",
   "property_type": "Int",
   "row_name": null,
   "value": "1"
  },
  {
   "_assign": null,
   "_comments": null,
   "_liked_by": null,
   "_user_tags": null,
   "creation": "2022-06-04 15:43:19.474589",
   "default_value": null,
   "doc_type": "Delivery Note",
   "docstatus": 0,
   "doctype_or_field": "DocField",
   "field_name": "sec_tax_breakup",
   "idx": 0,
   "modified": "2022-06-04 15:43:19.474589",
   "modified_by": "islam@erpcloud.systems",
   "name": "Delivery Note-sec_tax_breakup-permlevel",
   "owner": "islam@erpcloud.systems",
   "parent": null,
   "parentfield": null,
   "parenttype": null,
   "property": "permlevel",
   "property_type": "Int",
   "row_name": null,
   "value": "1"
  },
  {
   "_assign": null,
   "_comments": null,
   "_liked_by": null,
   "_user_tags": null,
   "creation": "2022-06-04 15:42:40.126360",
   "default_value": null,
   "doc_type": "Delivery Note",
   "docstatus": 0,
   "doctype_or_field": "DocField",
   "field_name": "taxes",
   "idx": 0,
   "modified": "2022-06-04 15:42:40.126360",
   "modified_by": "islam@erpcloud.systems",
   "name": "Delivery Note-taxes-permlevel",
   "owner": "islam@erpcloud.systems",
   "parent": null,
   "parentfield": null,
   "parenttype": null,
   "property": "permlevel",
   "property_type": "Int",
   "row_name": null,
   "value": "1"
  },
  {
   "_assign": null,
   "_comments": null,
   "_liked_by": null,
   "_user_tags": null,
   "creation": "2022-06-04 15:42:40.039269",
   "default_value": null,
   "doc_type": "Delivery Note",
   "docstatus": 0,
   "doctype_or_field": "DocField",
   "field_name": "taxes_and_charges",
   "idx": 0,
   "modified": "2022-06-04 15:42:40.039269",
   "modified_by": "islam@erpcloud.systems",
   "name": "Delivery Note-taxes_and_charges-permlevel",
   "owner": "islam@erpcloud.systems",
   "parent": null,
   "parentfield": null,
   "parenttype": null,
   "property": "permlevel",
   "property_type": "Int",
   "row_name": null,
   "value": "1"
  },
  {
   "_assign": null,
   "_comments": null,
   "_liked_by": null,
   "_user_tags": null,
   "creation": "2022-06-04 15:42:39.961626",
   "default_value": null,
   "doc_type": "Delivery Note",
   "docstatus": 0,
   "doctype_or_field": "DocField",
   "field_name": "shipping_rule",
   "idx": 0,
   "modified": "2022-06-04 15:42:39.961626",
   "modified_by": "islam@erpcloud.systems",
   "name": "Delivery Note-shipping_rule-permlevel",
   "owner": "islam@erpcloud.systems",
   "parent": null,
   "parentfield": null,
   "parenttype": null,
   "property": "permlevel",
   "property_type": "Int",
   "row_name": null,
   "value": "1"
  },
  {
   "_assign": null,
   "_comments": null,
   "_liked_by": null,
   "_user_tags": null,
   "creation": "2022-06-04 15:42:39.877311",
   "default_value": null,
   "doc_type": "Delivery Note",
   "docstatus": 0,
   "doctype_or_field": "DocField",
   "field_name": "tax_category",
   "idx": 0,
   "modified": "2022-06-04 15:42:39.877311",
   "modified_by": "islam@erpcloud.systems",
   "name": "Delivery Note-tax_category-permlevel",
   "owner": "islam@erpcloud.systems",
   "parent": null,
   "parentfield": null,
   "parenttype": null,
   "property": "permlevel",
   "property_type": "Int",
   "row_name": null,
   "value": "1"
  },
  {
   "_assign": null,
   "_comments": null,
   "_liked_by": null,
   "_user_tags": null,
   "creation": "2022-06-04 15:42:39.786726",
   "default_value": null,
   "doc_type": "Delivery Note",
   "docstatus": 0,
   "doctype_or_field": "DocField",
   "field_name": "taxes_section",
   "idx": 0,
   "modified": "2022-06-04 15:42:39.786726",
   "modified_by": "islam@erpcloud.systems",
   "name": "Delivery Note-taxes_section-permlevel",
   "owner": "islam@erpcloud.systems",
   "parent": null,
   "parentfield": null,
   "parenttype": null,
   "property": "permlevel",
   "property_type": "Int",
   "row_name": null,
   "value": "1"
  },
  {
   "_assign": null,
   "_comments": null,
   "_liked_by": null,
   "_user_tags": null,
   "creation": "2022-06-04 15:42:39.706944",
   "default_value": null,
   "doc_type": "Delivery Note",
   "docstatus": 0,
   "doctype_or_field": "DocField",
   "field_name": "net_total",
   "idx": 0,
   "modified": "2022-06-04 15:42:39.706944",
   "modified_by": "islam@erpcloud.systems",
   "name": "Delivery Note-net_total-permlevel",
   "owner": "islam@erpcloud.systems",
   "parent": null,
   "parentfield": null,
   "parenttype": null,
   "property": "permlevel",
   "property_type": "Int",
   "row_name": null,
   "value": "1"
  },
  {
   "_assign": null,
   "_comments": null,
   "_liked_by": null,
   "_user_tags": null,
   "creation": "2022-06-04 15:42:39.614077",
   "default_value": null,
   "doc_type": "Delivery Note",
   "docstatus": 0,
   "doctype_or_field": "DocField",
   "field_name": "total",
   "idx": 0,
   "modified": "2022-06-04 15:42:39.614077",
   "modified_by": "islam@erpcloud.systems",
   "name": "Delivery Note-total-permlevel",
   "owner": "islam@erpcloud.systems",
   "parent": null,
   "parentfield": null,
   "parenttype": null,
   "property": "permlevel",
   "property_type": "Int",
   "row_name": null,
   "value": "1"
  },
  {
   "_assign": null,
   "_comments": null,
   "_liked_by": null,
   "_user_tags": null,
   "creation": "2022-06-04 15:42:39.477986",
   "default_value": null,
   "doc_type": "Delivery Note",
   "docstatus": 0,
   "doctype_or_field": "DocField",
   "field_name": "total_net_weight",
   "idx": 0,
   "modified": "2022-06-04 15:42:39.477986",
   "modified_by": "islam@erpcloud.systems",
   "name": "Delivery Note-total_net_weight-permlevel",
   "owner": "islam@erpcloud.systems",
   "parent": null,
   "parentfield": null,
   "parenttype": null,
   "property": "permlevel",
   "property_type": "Int",
   "row_name": null,
   "value": "1"
  },
  {
   "_assign": null,
   "_comments": null,
   "_liked_by": null,
   "_user_tags": null,
   "creation": "2022-06-02 17:43:51.287163",
   "default_value": null,
   "doc_type": "Delivery Note",
   "docstatus": 0,
   "doctype_or_field": "DocField",
   "field_name": "tax_id",
   "idx": 0,
   "modified": "2022-06-02 17:43:51.287163",
   "modified_by": "islam@erpcloud.systems",
   "name": "Delivery Note-tax_id-print_hide",
   "owner": "islam@erpcloud.systems",
   "parent": null,
   "parentfield": null,
   "parenttype": null,
   "property": "print_hide",
   "property_type": "Check",
   "row_name": null,
   "value": "0"
  },
  {
   "_assign": null,
   "_comments": null,
   "_liked_by": null,
   "_user_tags": null,
   "creation": "2022-06-02 17:43:51.266297",
   "default_value": null,
   "doc_type": "Delivery Note",
   "docstatus": 0,
   "doctype_or_field": "DocField",
   "field_name": "tax_id",
   "idx": 0,
   "modified": "2022-06-02 17:43:51.266297",
   "modified_by": "islam@erpcloud.systems",
   "name": "Delivery Note-tax_id-hidden",
   "owner": "islam@erpcloud.systems",
   "parent": null,
   "parentfield": null,
   "parenttype": null,
   "property": "hidden",
   "property_type": "Check",
   "row_name": null,
   "value": "0"
  },
  {
   "_assign": null,
   "_comments": null,
   "_liked_by": null,
   "_user_tags": null,
   "creation": "2022-03-16 13:31:20.329166",
   "default_value": null,
   "doc_type": "Delivery Note",
   "docstatus": 0,
   "doctype_or_field": "DocField",
   "field_name": "disable_rounded_total",
   "idx": 0,
   "modified": "2022-03-16 13:31:20.329166",
   "modified_by": "Administrator",
   "name": "Delivery Note-disable_rounded_total-permlevel",
   "owner": "Administrator",
   "parent": null,
   "parentfield": null,
   "parenttype": null,
   "property": "permlevel",
   "property_type": "Int",
   "row_name": null,
   "value": "1"
  },
  {
   "_assign": null,
   "_comments": null,
   "_liked_by": null,
   "_user_tags": null,
   "creation": "2022-03-16 13:31:20.236081",
   "default_value": null,
   "doc_type": "Delivery Note",
   "docstatus": 0,
   "doctype_or_field": "DocField",
   "field_name": "in_words",
   "idx": 0,
   "modified": "2022-03-16 13:31:20.236081",
   "modified_by": "Administrator",
   "name": "Delivery Note-in_words-permlevel",
   "owner": "Administrator",
   "parent": null,
   "parentfield": null,
   "parenttype": null,
   "property": "permlevel",
   "property_type": "Int",
   "row_name": null,
   "value": "1"
  },
  {
   "_assign": null,
   "_comments": null,
   "_liked_by": null,
   "_user_tags": null,
   "creation": "2022-03-16 13:31:20.161507",
   "default_value": null,
   "doc_type": "Delivery Note",
   "docstatus": 0,
   "doctype_or_field": "DocField",
   "field_name": "rounded_total",
   "idx": 0,
   "modified": "2022-03-16 13:31:20.161507",
   "modified_by": "Administrator",
   "name": "Delivery Note-rounded_total-permlevel",
   "owner": "Administrator",
   "parent": null,
   "parentfield": null,
   "parenttype": null,
   "property": "permlevel",
   "property_type": "Int",
   "row_name": null,
   "value": "1"
  },
  {
   "_assign": null,
   "_comments": null,
   "_liked_by": null,
   "_user_tags": null,
   "creation": "2022-03-16 13:31:20.088395",
   "default_value": null,
   "doc_type": "Delivery Note",
   "docstatus": 0,
   "doctype_or_field": "DocField",
   "field_name": "rounding_adjustment",
   "idx": 0,
   "modified": "2022-03-16 13:31:20.088395",
   "modified_by": "Administrator",
   "name": "Delivery Note-rounding_adjustment-permlevel",
   "owner": "Administrator",
   "parent": null,
   "parentfield": null,
   "parenttype": null,
   "property": "permlevel",
   "property_type": "Int",
   "row_name": null,
   "value": "1"
  },
  {
   "_assign": null,
   "_comments": null,
   "_liked_by": null,
   "_user_tags": null,
   "creation": "2022-03-16 13:31:20.014384",
   "default_value": null,
   "doc_type": "Delivery Note",
   "docstatus": 0,
   "doctype_or_field": "DocField",
   "field_name": "grand_total",
   "idx": 0,
   "modified": "2022-03-16 13:31:20.014384",
   "modified_by": "Administrator",
   "name": "Delivery Note-grand_total-permlevel",
   "owner": "Administrator",
   "parent": null,
   "parentfield": null,
   "parenttype": null,
   "property": "permlevel",
   "property_type": "Int",
   "row_name": null,
   "value": "1"
  },
  {
   "_assign": null,
   "_comments": null,
   "_liked_by": null,
   "_user_tags": null,
   "creation": "2022-03-16 13:31:19.928987",
   "default_value": null,
   "doc_type": "Delivery Note",
   "docstatus": 0,
   "doctype_or_field": "DocField",
   "field_name": "base_in_words",
   "idx": 0,
   "modified": "2022-03-16 13:31:19.928987",
   "modified_by": "Administrator",
   "name": "Delivery Note-base_in_words-permlevel",
   "owner": "Administrator",
   "parent": null,
   "parentfield": null,
   "parenttype": null,
   "property": "permlevel",
   "property_type": "Int",
   "row_name": null,
   "value": "1"
  },
  {
   "_assign": null,
   "_comments": null,
   "_liked_by": null,
   "_user_tags": null,
   "creation": "2022-03-16 13:31:19.845889",
   "default_value": null,
   "doc_type": "Delivery Note",
   "docstatus": 0,
   "doctype_or_field": "DocField",
   "field_name": "base_rounded_total",
   "idx": 0,
   "modified": "2022-03-16 13:31:19.845889",
   "modified_by": "Administrator",
   "name": "Delivery Note-base_rounded_total-permlevel",
   "owner": "Administrator",
   "parent": null,
   "parentfield": null,
   "parenttype": null,
   "property": "permlevel",
   "property_type": "Int",
   "row_name": null,
   "value": "1"
  },
  {
   "_assign": null,
   "_comments": null,
   "_liked_by": null,
   "_user_tags": null,
   "creation": "2022-03-16 13:31:19.764581",
   "default_value": null,
   "doc_type": "Delivery Note",
   "docstatus": 0,
   "doctype_or_field": "DocField",
   "field_name": "base_rounding_adjustment",
   "idx": 0,
   "modified": "2022-03-16 13:31:19.764581",
   "modified_by": "Administrator",
   "name": "Delivery Note-base_rounding_adjustment-permlevel",
   "owner": "Administrator",
   "parent": null,
   "parentfield": null,
   "parenttype": null,
   "property": "permlevel",
   "property_type": "Int",
   "row_name": null,
   "value": "1"
  },
  {
   "_assign": null,
   "_comments": null,
   "_liked_by": null,
   "_user_tags": null,
   "creation": "2022-03-16 13:31:19.681476",
   "default_value": null,
   "doc_type": "Delivery Note",
   "docstatus": 0,
   "doctype_or_field": "DocField",
   "field_name": "base_grand_total",
   "idx": 0,
   "modified": "2022-03-16 13:31:19.681476",
   "modified_by": "Administrator",
   "name": "Delivery Note-base_grand_total-permlevel",
   "owner": "Administrator",
   "parent": null,
   "parentfield": null,
   "parenttype": null,
   "property": "permlevel",
   "property_type": "Int",
   "row_name": null,
   "value": "1"
  },
  {
   "_assign": null,
   "_comments": null,
   "_liked_by": null,
   "_user_tags": null,
   "creation": "2022-03-16 13:31:19.579050",
   "default_value": null,
   "doc_type": "Delivery Note",
   "docstatus": 0,
   "doctype_or_field": "DocField",
   "field_name": "section_break_49",
   "idx": 0,
   "modified": "2022-03-16 13:31:19.579050",
   "modified_by": "Administrator",
   "name": "Delivery Note-section_break_49-permlevel",
   "owner": "Administrator",
   "parent": null,
   "parentfield": null,
   "parenttype": null,
   "property": "permlevel",
   "property_type": "Int",
   "row_name": null,
   "value": "1"
  },
  {
   "_assign": null,
   "_comments": null,
   "_liked_by": null,
   "_user_tags": null,
   "creation": "2022-03-16 13:31:19.495878",
   "default_value": null,
   "doc_type": "Delivery Note",
   "docstatus": 0,
   "doctype_or_field": "DocField",
   "field_name": "total_taxes_and_charges",
   "idx": 0,
   "modified": "2022-03-16 13:31:19.495878",
   "modified_by": "Administrator",
   "name": "Delivery Note-total_taxes_and_charges-permlevel",
   "owner": "Administrator",
   "parent": null,
   "parentfield": null,
   "parenttype": null,
   "property": "permlevel",
   "property_type": "Int",
   "row_name": null,
   "value": "1"
  },
  {
   "_assign": null,
   "_comments": null,
   "_liked_by": null,
   "_user_tags": null,
   "creation": "2022-03-16 13:31:19.424170",
   "default_value": null,
   "doc_type": "Delivery Note",
   "docstatus": 0,
   "doctype_or_field": "DocField",
   "field_name": "base_total_taxes_and_charges",
   "idx": 0,
   "modified": "2022-03-16 13:31:19.424170",
   "modified_by": "Administrator",
   "name": "Delivery Note-base_total_taxes_and_charges-permlevel",
   "owner": "Administrator",
   "parent": null,
   "parentfield": null,
   "parenttype": null,
   "property": "permlevel",
   "property_type": "Int",
   "row_name": null,
   "value": "1"
  },
  {
   "_assign": null,
   "_comments": null,
   "_liked_by": null,
   "_user_tags": null,
   "creation": "2022-03-16 13:31:19.342064",
   "default_value": null,
   "doc_type": "Delivery Note",
   "docstatus": 0,
   "doctype_or_field": "DocField",
   "field_name": "base_net_total",
   "idx": 0,
   "modified": "2022-03-16 13:31:19.342064",
   "modified_by": "Administrator",
   "name": "Delivery Note-base_net_total-permlevel",
   "owner": "Administrator",
   "parent": null,
   "parentfield": null,
   "parenttype": null,
   "property": "permlevel",
   "property_type": "Int",
   "row_name": null,
   "value": "1"
  },
  {
   "_assign": null,
   "_comments": null,
   "_liked_by": null,
   "_user_tags": null,
   "creation": "2022-03-16 13:31:19.255646",
   "default_value": null,
   "doc_type": "Delivery Note",
   "docstatus": 0,
   "doctype_or_field": "DocField",
   "field_name": "base_total",
   "idx": 0,
   "modified": "2022-03-16 13:31:19.255646",
   "modified_by": "Administrator",
   "name": "Delivery Note-base_total-permlevel",
   "owner": "Administrator",
   "parent": null,
   "parentfield": null,
   "parenttype": null,
   "property": "permlevel",
   "property_type": "Int",
   "row_name": null,
   "value": "1"
  },
  {
   "_assign": null,
   "_comments": null,
   "_liked_by": null,
   "_user_tags": null,
   "creation": "2021-07-04 15:28:11.262093",
   "default_value": null,
   "doc_type": "Delivery Note",
   "docstatus": 0,
   "doctype_or_field": "DocType",
   "field_name": null,
   "idx": 0,
   "modified": "2021-07-04 15:28:11.262093",
   "modified_by": "Administrator",
   "name": "Delivery Note-main-default_print_format",
   "owner": "Administrator",
   "parent": null,
   "parentfield": null,
   "parenttype": null,
   "property": "default_print_format",
   "property_type": "Data",
   "row_name": null,
   "value": "Delivery Note (EN)"
  },
  {
   "_assign": null,
   "_comments": null,
   "_liked_by": null,
   "_user_tags": null,
   "creation": "2021-03-17 19:08:05.736475",
   "default_value": null,
   "doc_type": "Delivery Note",
   "docstatus": 0,
   "doctype_or_field": "DocField",
   "field_name": "naming_series",
   "idx": 0,
   "modified": "2021-03-17 19:08:05.736475",
   "modified_by": "Administrator",
   "name": "Delivery Note-naming_series-options",
   "owner": "Administrator",
   "parent": null,
   "parentfield": null,
   "parenttype": null,
   "property": "options",
   "property_type": "Text",
   "row_name": null,
   "value": "MAT-DN-.YYYY.-"
  }
 ],
 "sync_on_migrate": 1
}